augustus/Gaius.py
augustus/__init__.py
augustus/config.py
augustus/constants.py
augustus/environment.py
augustus/event_engine.py
augustus/builtin/__init__.py
augustus/builtin/optimizer.py
augustus/builtin/backtest_forex/__init__.py
augustus/builtin/backtest_forex/calculate_func.py
augustus/builtin/backtest_forex/forex_bar.py
augustus/builtin/backtest_forex/forex_broker.py
augustus/builtin/backtest_forex/forex_log.py
augustus/builtin/backtest_forex/forex_recorder.py
augustus/builtin/backtest_forex/forex_recorder_series.py
augustus/builtin/backtest_stock/__init__.py
augustus/builtin/backtest_stock/stock_bar.py
augustus/builtin/backtest_stock/stock_broker.py
augustus/builtin/backtest_stock/stock_limit_filter_risk_manager.py
augustus/builtin/backtest_stock/stock_log.py
augustus/builtin/backtest_stock/stock_recorder.py
augustus/builtin/backtest_stock/stock_recorder_series.py
augustus/builtin/data_readers/__init__.py
augustus/builtin/data_readers/csvreader.py
augustus/builtin/data_readers/mongodb_reader.py
augustus/builtin/mongodb_saver/__init__.py
augustus/builtin/mongodb_saver/csv_saver.py
augustus/builtin/mongodb_saver/mongodb_config.py
augustus/builtin/mongodb_saver/oanda_saver.py
augustus/builtin/mongodb_saver/tushare_saver.py
augustus/builtin/mongodb_saver/utils.py
augustus/builtin/plotters/__init__.py
augustus/builtin/plotters/by_matplotlib.py
augustus/builtin/plotters/by_plotly.py
augustus/custom/__init__.py
augustus/custom/alpha101_cleaner.py
augustus/custom/analysis.py
augustus/custom/backtest.py
augustus/custom/cleaner_sma.py
augustus/custom/cleaner_talib.py
augustus/custom/forward_analysis.py
augustus/custom/oanda_bar.py
augustus/custom/oanda_broker.py
augustus/custom/oanda_reader.py
augustus/custom/oanda_recorder.py
augustus/custom/trade_log_analysis.py
augustus/custom/api/__init__.py
augustus/custom/api/oanda_api.py
augustus/system/__init__.py
augustus/system/base_broker.py
augustus/system/base_cleaner.py
augustus/system/base_reader.py
augustus_quant-1.0.0.dist-info/LICENSE
augustus_quant-1.0.0.dist-info/METADATA
augustus_quant-1.0.0.dist-info/WHEEL
augustus_quant-1.0.0.dist-info/top_level.txt
augustus_quant-1.0.0.dist-info/RECORD
